Metadata-Version: 2.1
Name: degtrig
Version: 0.0.3
Summary: Adds all of the trigonometric functions using degrees instead of radians.
Home-page: https://github.com/abhinav-gg/StupidPipPackages/DegTrig
Author: Abhinav G
Author-email: agupta.cam7@gmail.com
License: MIT
Keywords: trigonometry,radians,degrees,trig,convert,radians to degrees,degrees to radians,deg,rad,hyperbolic,hyperbolic functions
Platform: UNKNOWN
Classifier: Programming Language :: Python :: 3
Classifier: License :: OSI Approved :: MIT License
Classifier: Operating System :: OS Independent
